<?xml version="1.0" encoding="UTF-8"?>
<export version="D">
  <design>
    <source>/Users/margaret/Documents/EnergyMonitoring/HappyDayNeighbors/HappyDay_Energy_PCB/HappyDay_Energy_PCB.sch</source>
    <date>Thursday, December 07, 2017 'AMt' 04:27:14 AM</date>
    <tool>Eeschema 4.0.7</tool>
    <sheet number="1" name="/" tstamps="/">
      <title_block>
        <title/>
        <company/>
        <rev/>
        <date/>
        <source>HappyDay_Energy_PCB.sch</source>
        <comment number="1" value=""/>
        <comment number="2" value=""/>
        <comment number="3" value=""/>
        <comment number="4" value=""/>
      </title_block>
    </sheet>
    <sheet number="2" name="/ATM90_Circuit/" tstamps="/5A1041CA/">
      <title_block>
        <title/>
        <company/>
        <rev/>
        <date/>
        <source>ATM90_Circuit.sch</source>
        <comment number="1" value=""/>
        <comment number="2" value=""/>
        <comment number="3" value=""/>
        <comment number="4" value=""/>
      </title_block>
    </sheet>
  </design>
  <components>
    <comp ref="R11">
      <value>1K</value>
      <footprint>Resistors_SMD:R_0805_HandSoldering</footprint>
      <fields>
        <field name="PN">R</field>
      </fields>
      <libsource lib="device" part="R"/>
      <sheetpath names="/" tstamps="/"/>
      <tstamp>5A10E69F</tstamp>
    </comp>
    <comp ref="C1">
      <value>.033u</value>
      <footprint>Capacitors_SMD:C_0805_HandSoldering</footprint>
      <fields>
        <field name="PN">C</field>
      </fields>
      <libsource lib="device" part="C"/>
      <sheetpath names="/" tstamps="/"/>
      <tstamp>5A119335</tstamp>
    </comp>
    <comp ref="RV1">
      <value>Varistor</value>
      <footprint>HappyDayEnergyMonitor:MOV</footprint>
      <fields>
        <field name="PN">B72660M0251K072</field>
      </fields>
      <libsource lib="device" part="Varistor"/>
      <sheetpath names="/" tstamps="/"/>
      <tstamp>5A11BE8A</tstamp>
    </comp>
    <comp ref="R12">
      <value>1K</value>
      <footprint>Resistors_SMD:R_0805_HandSoldering</footprint>
      <fields>
        <field name="PN">R</field>
      </fields>
      <libsource lib="device" part="R"/>
      <sheetpath names="/" tstamps="/"/>
      <tstamp>5A11C444</tstamp>
    </comp>
    <comp ref="C2">
      <value>.033u</value>
      <footprint>Capacitors_SMD:C_0805_HandSoldering</footprint>
      <fields>
        <field name="PN">C</field>
      </fields>
      <libsource lib="device" part="C"/>
      <sheetpath names="/" tstamps="/"/>
      <tstamp>5A11C44A</tstamp>
    </comp>
    <comp ref="L1">
      <value>Ferrite_Bead_Small</value>
      <footprint>Capacitors_SMD:C_1206_HandSoldering</footprint>
      <fields>
        <field name="PN">HI1206T500R-10</field>
      </fields>
      <libsource lib="device" part="Ferrite_Bead_Small"/>
      <sheetpath names="/" tstamps="/"/>
      <tstamp>5A11C7F8</tstamp>
    </comp>
    <comp ref="RV2">
      <value>Varistor</value>
      <footprint>HappyDayEnergyMonitor:MOV</footprint>
      <fields>
        <field name="PN">B72660M0251K072</field>
      </fields>
      <libsource lib="device" part="Varistor"/>
      <sheetpath names="/" tstamps="/"/>
      <tstamp>5A11CB55</tstamp>
    </comp>
    <comp ref="F1">
      <value>Polyfuse</value>
      <footprint>HappyDayEnergyMonitor:POLYFUSE</footprint>
      <fields>
        <field name="PN">LVR005NK</field>
      </fields>
      <libsource lib="device" part="Polyfuse"/>
      <sheetpath names="/" tstamps="/"/>
      <tstamp>5A120D00</tstamp>
    </comp>
    <comp ref="R1">
      <value>12</value>
      <footprint>Resistors_SMD:R_0805_HandSoldering</footprint>
      <fields>
        <field name="PN">RL1220S-120-F</field>
      </fields>
      <libsource lib="device" part="R"/>
      <sheetpath names="/" tstamps="/"/>
      <tstamp>5A12DA2B</tstamp>
    </comp>
    <comp ref="R13">
      <value>330</value>
      <footprint>Resistors_SMD:R_0805_HandSoldering</footprint>
      <fields>
        <field name="PN">R</field>
      </fields>
      <libsource lib="device" part="R"/>
      <sheetpath names="/" tstamps="/"/>
      <tstamp>5A186D61</tstamp>
    </comp>
    <comp ref="D2">
      <value>IND_LED</value>
      <footprint>Capacitors_SMD:C_1206_HandSoldering</footprint>
      <fields>
        <field name="PN">LED</field>
      </fields>
      <libsource lib="device" part="LED"/>
      <sheetpath names="/" tstamps="/"/>
      <tstamp>5A186E2C</tstamp>
    </comp>
    <comp ref="R3">
      <value>220K</value>
      <footprint>Resistors_SMD:R_1206_HandSoldering</footprint>
      <fields>
        <field name="PN">R</field>
      </fields>
      <libsource lib="device" part="R"/>
      <sheetpath names="/" tstamps="/"/>
      <tstamp>5A1C8053</tstamp>
    </comp>
    <comp ref="U1">
      <value>120VAC-&gt;3.3VDC REG</value>
      <footprint>HappyDayEnergyMonitor:RAC03-GA</footprint>
      <fields>
        <field name="PN">RAC03-3.3SGA</field>
      </fields>
      <libsource lib="atm90e26" part="RAC03-3.3SGA"/>
      <sheetpath names="/" tstamps="/"/>
      <tstamp>5A1C9875</tstamp>
    </comp>
    <comp ref="C5">
      <value>.001u</value>
      <footprint>Capacitors_SMD:C_0805_HandSoldering</footprint>
      <fields>
        <field name="PN">202R18W102KV4E</field>
      </fields>
      <libsource lib="device" part="C"/>
      <sheetpath names="/" tstamps="/"/>
      <tstamp>5A1C9923</tstamp>
    </comp>
    <comp ref="C3">
      <value>.001u</value>
      <footprint>Capacitors_SMD:C_0805_HandSoldering</footprint>
      <fields>
        <field name="PN">202R18W102KV4E</field>
      </fields>
      <libsource lib="device" part="C"/>
      <sheetpath names="/" tstamps="/"/>
      <tstamp>5A1C99F2</tstamp>
    </comp>
    <comp ref="C4">
      <value>.1u</value>
      <footprint>Capacitors_SMD:C_0805_HandSoldering</footprint>
      <fields>
        <field name="PN">GRM32DR72H104KW10L</field>
      </fields>
      <libsource lib="device" part="C"/>
      <sheetpath names="/" tstamps="/"/>
      <tstamp>5A1C9B61</tstamp>
    </comp>
    <comp ref="U2">
      <value>dc-dc</value>
      <footprint>HappyDayEnergyMonitor:DC-DC</footprint>
      <fields>
        <field name="PN">CRE1S0505S3C</field>
      </fields>
      <libsource lib="dc-dc" part="dc-dc"/>
      <sheetpath names="/" tstamps="/"/>
      <tstamp>5A1D75ED</tstamp>
    </comp>
    <comp ref="R5">
      <value>220K</value>
      <footprint>Resistors_SMD:R_1206_HandSoldering</footprint>
      <fields>
        <field name="PN">R</field>
      </fields>
      <libsource lib="device" part="R"/>
      <sheetpath names="/" tstamps="/"/>
      <tstamp>5A1EAA0E</tstamp>
    </comp>
    <comp ref="R7">
      <value>220K</value>
      <footprint>Resistors_SMD:R_1206_HandSoldering</footprint>
      <fields>
        <field name="PN">R</field>
      </fields>
      <libsource lib="device" part="R"/>
      <sheetpath names="/" tstamps="/"/>
      <tstamp>5A1EAAC3</tstamp>
    </comp>
    <comp ref="R9">
      <value>220K</value>
      <footprint>Resistors_SMD:R_1206_HandSoldering</footprint>
      <fields>
        <field name="PN">R</field>
      </fields>
      <libsource lib="device" part="R"/>
      <sheetpath names="/" tstamps="/"/>
      <tstamp>5A1EABAC</tstamp>
    </comp>
    <comp ref="R4">
      <value>220K</value>
      <footprint>Resistors_SMD:R_1206_HandSoldering</footprint>
      <fields>
        <field name="PN">R</field>
      </fields>
      <libsource lib="device" part="R"/>
      <sheetpath names="/" tstamps="/"/>
      <tstamp>5A1EAC4B</tstamp>
    </comp>
    <comp ref="R6">
      <value>220K</value>
      <footprint>Resistors_SMD:R_1206_HandSoldering</footprint>
      <fields>
        <field name="PN">R</field>
      </fields>
      <libsource lib="device" part="R"/>
      <sheetpath names="/" tstamps="/"/>
      <tstamp>5A1EAD0D</tstamp>
    </comp>
    <comp ref="R8">
      <value>220K</value>
      <footprint>Resistors_SMD:R_1206_HandSoldering</footprint>
      <fields>
        <field name="PN">R</field>
      </fields>
      <libsource lib="device" part="R"/>
      <sheetpath names="/" tstamps="/"/>
      <tstamp>5A1EADB7</tstamp>
    </comp>
    <comp ref="R10">
      <value>220K</value>
      <footprint>Resistors_SMD:R_1206_HandSoldering</footprint>
      <fields>
        <field name="PN">R</field>
      </fields>
      <libsource lib="device" part="R"/>
      <sheetpath names="/" tstamps="/"/>
      <tstamp>5A1EAE66</tstamp>
    </comp>
    <comp ref="J2">
      <value>TRS3.5Female</value>
      <footprint>HappyDayEnergyMonitor:Audio-Jack</footprint>
      <fields>
        <field name="PN">SJ-3523-SMT-TR</field>
      </fields>
      <libsource lib="atm90e26" part="TRS3.5Female"/>
      <sheetpath names="/" tstamps="/"/>
      <tstamp>5A2057E2</tstamp>
    </comp>
    <comp ref="R2">
      <value>12</value>
      <footprint>Resistors_SMD:R_0805_HandSoldering</footprint>
      <fields>
        <field name="PN">RL1220S-120-F</field>
      </fields>
      <libsource lib="device" part="R"/>
      <sheetpath names="/" tstamps="/"/>
      <tstamp>5A205D25</tstamp>
    </comp>
    <comp ref="J3">
      <value>TRS3.5Female</value>
      <footprint>HappyDayEnergyMonitor:Audio-Jack</footprint>
      <fields>
        <field name="PN">SJ-3523-SMT-TR</field>
      </fields>
      <libsource lib="atm90e26" part="TRS3.5Female"/>
      <sheetpath names="/" tstamps="/"/>
      <tstamp>5A205D36</tstamp>
    </comp>
    <comp ref="J1">
      <value>Conn_01x03</value>
      <footprint>HappyDayEnergyMonitor:3PinConnector</footprint>
      <fields>
        <field name="PN">OSTTE030161</field>
      </fields>
      <libsource lib="conn" part="Conn_01x03"/>
      <sheetpath names="/" tstamps="/"/>
      <tstamp>5A215440</tstamp>
    </comp>
    <comp ref="TP1">
      <value>3.3V_A</value>
      <footprint>Connectors_TestPoints:Test_Point_Pad_d2.0mm</footprint>
      <fields>
        <field name="PN">X</field>
      </fields>
      <libsource lib="device" part="TEST"/>
      <sheetpath names="/" tstamps="/"/>
      <tstamp>5A22A137</tstamp>
    </comp>
    <comp ref="TP2">
      <value>GNDA</value>
      <footprint>Connectors_TestPoints:Test_Point_Pad_d2.0mm</footprint>
      <fields>
        <field name="PN">X</field>
      </fields>
      <libsource lib="device" part="TEST"/>
      <sheetpath names="/" tstamps="/"/>
      <tstamp>5A22A5EB</tstamp>
    </comp>
    <comp ref="TP3">
      <value>LO_SAMP</value>
      <footprint>Connectors_TestPoints:Test_Point_Pad_d2.0mm</footprint>
      <fields>
        <field name="PN">X</field>
      </fields>
      <libsource lib="device" part="TEST"/>
      <sheetpath names="/" tstamps="/"/>
      <tstamp>5A22AA32</tstamp>
    </comp>
    <comp ref="TP4">
      <value>L1_SAMP</value>
      <footprint>Connectors_TestPoints:Test_Point_Pad_d2.0mm</footprint>
      <fields>
        <field name="PN">x</field>
      </fields>
      <libsource lib="device" part="TEST"/>
      <sheetpath names="/" tstamps="/"/>
      <tstamp>5A22AFE3</tstamp>
    </comp>
    <comp ref="TP6">
      <value>I1P_0</value>
      <footprint>Connectors_TestPoints:Test_Point_Pad_d2.0mm</footprint>
      <fields>
        <field name="PN">x</field>
      </fields>
      <libsource lib="device" part="TEST"/>
      <sheetpath names="/" tstamps="/"/>
      <tstamp>5A22B653</tstamp>
    </comp>
    <comp ref="TP7">
      <value>I1N_0</value>
      <footprint>Connectors_TestPoints:Test_Point_Pad_d2.0mm</footprint>
      <fields>
        <field name="PN">x</field>
      </fields>
      <libsource lib="device" part="TEST"/>
      <sheetpath names="/" tstamps="/"/>
      <tstamp>5A22B7E2</tstamp>
    </comp>
    <comp ref="TP8">
      <value>I1P_1</value>
      <footprint>Connectors_TestPoints:Test_Point_Pad_d2.0mm</footprint>
      <fields>
        <field name="PN">x</field>
      </fields>
      <libsource lib="device" part="TEST"/>
      <sheetpath names="/" tstamps="/"/>
      <tstamp>5A22E009</tstamp>
    </comp>
    <comp ref="TP9">
      <value>I1N_1</value>
      <footprint>Connectors_TestPoints:Test_Point_Pad_d2.0mm</footprint>
      <fields>
        <field name="PN">x</field>
      </fields>
      <libsource lib="device" part="TEST"/>
      <sheetpath names="/" tstamps="/"/>
      <tstamp>5A22F1E1</tstamp>
    </comp>
    <comp ref="TP10">
      <value>3.3V_D</value>
      <footprint>Connectors_TestPoints:Test_Point_Pad_d2.0mm</footprint>
      <fields>
        <field name="PN">x</field>
      </fields>
      <libsource lib="device" part="TEST"/>
      <sheetpath names="/" tstamps="/"/>
      <tstamp>5A2303DE</tstamp>
    </comp>
    <comp ref="TP11">
      <value>GND_D</value>
      <footprint>Connectors_TestPoints:Test_Point_Pad_d2.0mm</footprint>
      <fields>
        <field name="PN">x</field>
      </fields>
      <libsource lib="device" part="TEST"/>
      <sheetpath names="/" tstamps="/"/>
      <tstamp>5A230D1F</tstamp>
    </comp>
    <comp ref="J10">
      <value>GS3</value>
      <footprint>Connectors:GS3</footprint>
      <fields>
        <field name="PN">X</field>
      </fields>
      <libsource lib="conn" part="GS3"/>
      <sheetpath names="/ATM90_Circuit/" tstamps="/5A1041CA/"/>
      <tstamp>5A10541E</tstamp>
    </comp>
    <comp ref="J11">
      <value>GS3</value>
      <footprint>Connectors:GS3</footprint>
      <fields>
        <field name="PN">X</field>
      </fields>
      <libsource lib="conn" part="GS3"/>
      <sheetpath names="/ATM90_Circuit/" tstamps="/5A1041CA/"/>
      <tstamp>5A105459</tstamp>
    </comp>
    <comp ref="C11">
      <value>.1u</value>
      <footprint>Capacitors_SMD:C_0805_HandSoldering</footprint>
      <fields>
        <field name="PN">C</field>
      </fields>
      <libsource lib="device" part="C"/>
      <sheetpath names="/ATM90_Circuit/" tstamps="/5A1041CA/"/>
      <tstamp>5A1061DE</tstamp>
    </comp>
    <comp ref="C9">
      <value>10u</value>
      <footprint>Capacitors_SMD:C_0805_HandSoldering</footprint>
      <fields>
        <field name="PN">C</field>
      </fields>
      <libsource lib="device" part="CP1"/>
      <sheetpath names="/ATM90_Circuit/" tstamps="/5A1041CA/"/>
      <tstamp>5A106256</tstamp>
    </comp>
    <comp ref="C12">
      <value>.1u</value>
      <footprint>Capacitors_SMD:C_0805_HandSoldering</footprint>
      <fields>
        <field name="PN">C</field>
      </fields>
      <libsource lib="device" part="C"/>
      <sheetpath names="/ATM90_Circuit/" tstamps="/5A1041CA/"/>
      <tstamp>5A108411</tstamp>
    </comp>
    <comp ref="C10">
      <value>10u</value>
      <footprint>Capacitors_SMD:C_0805_HandSoldering</footprint>
      <fields>
        <field name="PN">C</field>
      </fields>
      <libsource lib="device" part="CP1"/>
      <sheetpath names="/ATM90_Circuit/" tstamps="/5A1041CA/"/>
      <tstamp>5A108417</tstamp>
    </comp>
    <comp ref="C8">
      <value>.1u</value>
      <footprint>Capacitors_SMD:C_0805_HandSoldering</footprint>
      <fields>
        <field name="PN">C</field>
      </fields>
      <libsource lib="device" part="C"/>
      <sheetpath names="/ATM90_Circuit/" tstamps="/5A1041CA/"/>
      <tstamp>5A1086D4</tstamp>
    </comp>
    <comp ref="Y1">
      <value>Crystal_Small</value>
      <footprint>HappyDayEnergyMonitor:Crystal</footprint>
      <fields>
        <field name="PN">535-9865-1-ND</field>
      </fields>
      <libsource lib="device" part="Crystal_Small"/>
      <sheetpath names="/ATM90_Circuit/" tstamps="/5A1041CA/"/>
      <tstamp>5A10B8C0</tstamp>
    </comp>
    <comp ref="C13">
      <value>18p</value>
      <footprint>Capacitors_SMD:C_0805_HandSoldering</footprint>
      <fields>
        <field name="PN">C</field>
      </fields>
      <libsource lib="device" part="C"/>
      <sheetpath names="/ATM90_Circuit/" tstamps="/5A1041CA/"/>
      <tstamp>5A10B9B0</tstamp>
    </comp>
    <comp ref="C14">
      <value>18p</value>
      <footprint>Capacitors_SMD:C_0805_HandSoldering</footprint>
      <fields>
        <field name="PN">C</field>
      </fields>
      <libsource lib="device" part="C"/>
      <sheetpath names="/ATM90_Circuit/" tstamps="/5A1041CA/"/>
      <tstamp>5A10B9F6</tstamp>
    </comp>
    <comp ref="J17">
      <value>GS3</value>
      <footprint>Connectors:GS3</footprint>
      <fields>
        <field name="PN">X</field>
      </fields>
      <libsource lib="conn" part="GS3"/>
      <sheetpath names="/ATM90_Circuit/" tstamps="/5A1041CA/"/>
      <tstamp>5A10DFE3</tstamp>
    </comp>
    <comp ref="J18">
      <value>GS3</value>
      <footprint>Connectors:GS3</footprint>
      <fields>
        <field name="PN">X</field>
      </fields>
      <libsource lib="conn" part="GS3"/>
      <sheetpath names="/ATM90_Circuit/" tstamps="/5A1041CA/"/>
      <tstamp>5A10DFE9</tstamp>
    </comp>
    <comp ref="C20">
      <value>.1u</value>
      <footprint>Capacitors_SMD:C_0805_HandSoldering</footprint>
      <fields>
        <field name="PN">C</field>
      </fields>
      <libsource lib="device" part="C"/>
      <sheetpath names="/ATM90_Circuit/" tstamps="/5A1041CA/"/>
      <tstamp>5A10E011</tstamp>
    </comp>
    <comp ref="C18">
      <value>10u</value>
      <footprint>Capacitors_SMD:C_0805_HandSoldering</footprint>
      <fields>
        <field name="PN">C</field>
      </fields>
      <libsource lib="device" part="CP1"/>
      <sheetpath names="/ATM90_Circuit/" tstamps="/5A1041CA/"/>
      <tstamp>5A10E017</tstamp>
    </comp>
    <comp ref="C21">
      <value>.1u</value>
      <footprint>Capacitors_SMD:C_0805_HandSoldering</footprint>
      <fields>
        <field name="PN">C</field>
      </fields>
      <libsource lib="device" part="C"/>
      <sheetpath names="/ATM90_Circuit/" tstamps="/5A1041CA/"/>
      <tstamp>5A10E031</tstamp>
    </comp>
    <comp ref="C19">
      <value>10u</value>
      <footprint>Capacitors_SMD:C_0805_HandSoldering</footprint>
      <fields>
        <field name="PN">C</field>
      </fields>
      <libsource lib="device" part="CP1"/>
      <sheetpath names="/ATM90_Circuit/" tstamps="/5A1041CA/"/>
      <tstamp>5A10E037</tstamp>
    </comp>
    <comp ref="C17">
      <value>.1u</value>
      <footprint>Capacitors_SMD:C_0805_HandSoldering</footprint>
      <fields>
        <field name="PN">C</field>
      </fields>
      <libsource lib="device" part="C"/>
      <sheetpath names="/ATM90_Circuit/" tstamps="/5A1041CA/"/>
      <tstamp>5A10E04E</tstamp>
    </comp>
    <comp ref="Y2">
      <value>Crystal_Small</value>
      <footprint>HappyDayEnergyMonitor:Crystal</footprint>
      <fields>
        <field name="PN">535-9865-1-ND</field>
      </fields>
      <libsource lib="device" part="Crystal_Small"/>
      <sheetpath names="/ATM90_Circuit/" tstamps="/5A1041CA/"/>
      <tstamp>5A10EF14</tstamp>
    </comp>
    <comp ref="C15">
      <value>18p</value>
      <footprint>Capacitors_SMD:C_0805_HandSoldering</footprint>
      <fields>
        <field name="PN">C</field>
      </fields>
      <libsource lib="device" part="C"/>
      <sheetpath names="/ATM90_Circuit/" tstamps="/5A1041CA/"/>
      <tstamp>5A10EF1A</tstamp>
    </comp>
    <comp ref="C16">
      <value>18p</value>
      <footprint>Capacitors_SMD:C_0805_HandSoldering</footprint>
      <fields>
        <field name="PN">C</field>
      </fields>
      <libsource lib="device" part="C"/>
      <sheetpath names="/ATM90_Circuit/" tstamps="/5A1041CA/"/>
      <tstamp>5A10EF20</tstamp>
    </comp>
    <comp ref="L2">
      <value>L_Core_Ferrite_Small</value>
      <footprint>Capacitors_SMD:C_0805_HandSoldering</footprint>
      <fields>
        <field name="PN">MH2029-601Y</field>
      </fields>
      <libsource lib="device" part="L_Core_Ferrite_Small"/>
      <sheetpath names="/ATM90_Circuit/" tstamps="/5A1041CA/"/>
      <tstamp>5A14FB02</tstamp>
    </comp>
    <comp ref="L3">
      <value>L_Core_Ferrite_Small</value>
      <footprint>Capacitors_SMD:C_0805_HandSoldering</footprint>
      <fields>
        <field name="PN">BLM15AG100SN1D</field>
      </fields>
      <libsource lib="device" part="L_Core_Ferrite_Small"/>
      <sheetpath names="/ATM90_Circuit/" tstamps="/5A1041CA/"/>
      <tstamp>5A187DEF</tstamp>
    </comp>
    <comp ref="R14">
      <value>51</value>
      <footprint>Resistors_SMD:R_0805_HandSoldering</footprint>
      <fields>
        <field name="PN">R</field>
      </fields>
      <libsource lib="device" part="R"/>
      <sheetpath names="/ATM90_Circuit/" tstamps="/5A1041CA/"/>
      <tstamp>5A1A07B7</tstamp>
    </comp>
    <comp ref="R15">
      <value>51</value>
      <footprint>Resistors_SMD:R_0805_HandSoldering</footprint>
      <fields>
        <field name="PN">R</field>
      </fields>
      <libsource lib="device" part="R"/>
      <sheetpath names="/ATM90_Circuit/" tstamps="/5A1041CA/"/>
      <tstamp>5A1A0AAF</tstamp>
    </comp>
    <comp ref="R16">
      <value>51</value>
      <footprint>Resistors_SMD:R_0805_HandSoldering</footprint>
      <fields>
        <field name="PN">R</field>
      </fields>
      <libsource lib="device" part="R"/>
      <sheetpath names="/ATM90_Circuit/" tstamps="/5A1041CA/"/>
      <tstamp>5A1A0B32</tstamp>
    </comp>
    <comp ref="R17">
      <value>51</value>
      <footprint>Resistors_SMD:R_0805_HandSoldering</footprint>
      <fields>
        <field name="PN">R</field>
      </fields>
      <libsource lib="device" part="R"/>
      <sheetpath names="/ATM90_Circuit/" tstamps="/5A1041CA/"/>
      <tstamp>5A1A0BB8</tstamp>
    </comp>
    <comp ref="R19">
      <value>51</value>
      <footprint>Resistors_SMD:R_0805_HandSoldering</footprint>
      <fields>
        <field name="PN">R</field>
      </fields>
      <libsource lib="device" part="R"/>
      <sheetpath names="/ATM90_Circuit/" tstamps="/5A1041CA/"/>
      <tstamp>5A1A156A</tstamp>
    </comp>
    <comp ref="R20">
      <value>51</value>
      <footprint>Resistors_SMD:R_0805_HandSoldering</footprint>
      <fields>
        <field name="PN">R</field>
      </fields>
      <libsource lib="device" part="R"/>
      <sheetpath names="/ATM90_Circuit/" tstamps="/5A1041CA/"/>
      <tstamp>5A1A1631</tstamp>
    </comp>
    <comp ref="R21">
      <value>51</value>
      <footprint>Resistors_SMD:R_0805_HandSoldering</footprint>
      <fields>
        <field name="PN">R</field>
      </fields>
      <libsource lib="device" part="R"/>
      <sheetpath names="/ATM90_Circuit/" tstamps="/5A1041CA/"/>
      <tstamp>5A1A16C5</tstamp>
    </comp>
    <comp ref="R22">
      <value>51</value>
      <footprint>Resistors_SMD:R_0805_HandSoldering</footprint>
      <fields>
        <field name="PN">R</field>
      </fields>
      <libsource lib="device" part="R"/>
      <sheetpath names="/ATM90_Circuit/" tstamps="/5A1041CA/"/>
      <tstamp>5A1A175A</tstamp>
    </comp>
    <comp ref="R23">
      <value>51</value>
      <footprint>Resistors_SMD:R_0805_HandSoldering</footprint>
      <fields>
        <field name="PN">R</field>
      </fields>
      <libsource lib="device" part="R"/>
      <sheetpath names="/ATM90_Circuit/" tstamps="/5A1041CA/"/>
      <tstamp>5A1A17F2</tstamp>
    </comp>
    <comp ref="C6">
      <value>.1u</value>
      <footprint>Capacitors_SMD:C_0805_HandSoldering</footprint>
      <fields>
        <field name="PN">C</field>
      </fields>
      <libsource lib="device" part="C"/>
      <sheetpath names="/ATM90_Circuit/" tstamps="/5A1041CA/"/>
      <tstamp>5A1A1ECF</tstamp>
    </comp>
    <comp ref="C7">
      <value>.1u</value>
      <footprint>Capacitors_SMD:C_0805_HandSoldering</footprint>
      <fields>
        <field name="PN">C</field>
      </fields>
      <libsource lib="device" part="C"/>
      <sheetpath names="/ATM90_Circuit/" tstamps="/5A1041CA/"/>
      <tstamp>5A1A268E</tstamp>
    </comp>
    <comp ref="R18">
      <value>51</value>
      <footprint>Resistors_SMD:R_0805_HandSoldering</footprint>
      <fields>
        <field name="PN">R</field>
      </fields>
      <libsource lib="device" part="R"/>
      <sheetpath names="/ATM90_Circuit/" tstamps="/5A1041CA/"/>
      <tstamp>5A1A0C41</tstamp>
    </comp>
    <comp ref="R24">
      <value>10K</value>
      <footprint>Capacitors_SMD:C_0805_HandSoldering</footprint>
      <fields>
        <field name="PN">R</field>
      </fields>
      <libsource lib="device" part="R"/>
      <sheetpath names="/ATM90_Circuit/" tstamps="/5A1041CA/"/>
      <tstamp>5A20A670</tstamp>
    </comp>
    <comp ref="U4">
      <value>FeatherHuzzah</value>
      <footprint>HappyDayEnergyMonitor:ADAFRUIT_FEATHER</footprint>
      <fields>
        <field name="PN">x</field>
      </fields>
      <libsource lib="atm90e26" part="FeatherHuzzah"/>
      <sheetpath names="/ATM90_Circuit/" tstamps="/5A1041CA/"/>
      <tstamp>5A21C500</tstamp>
    </comp>
    <comp ref="M2">
      <value>ATM90E26_ATM90E26</value>
      <footprint>HappyDayEnergyMonitor:SSOP-28_5.3x10.2mm_Pitch0.65mm</footprint>
      <fields>
        <field name="PN">ATM90E26-YU-B</field>
      </fields>
      <libsource lib="ATM90E26_Featherwing" part="ATM90E26_ATM90E26"/>
      <sheetpath names="/ATM90_Circuit/" tstamps="/5A1041CA/"/>
      <tstamp>5A220C81</tstamp>
    </comp>
    <comp ref="M1">
      <value>ATM90E26_ATM90E26</value>
      <footprint>HappyDayEnergyMonitor:SSOP-28_5.3x10.2mm_Pitch0.65mm</footprint>
      <fields>
        <field name="PN">ATM90E26-YU-B</field>
      </fields>
      <libsource lib="ATM90E26_Featherwing" part="ATM90E26_ATM90E26"/>
      <sheetpath names="/ATM90_Circuit/" tstamps="/5A1041CA/"/>
      <tstamp>5A2210DD</tstamp>
    </comp>
    <comp ref="U3">
      <value>Si865</value>
      <footprint>HappyDayEnergyMonitor:Si865</footprint>
      <fields>
        <field name="PN">SI8652AB-B-IS1</field>
      </fields>
      <libsource lib="si865" part="Si8655"/>
      <sheetpath names="/ATM90_Circuit/" tstamps="/5A1041CA/"/>
      <tstamp>5A2219D1</tstamp>
    </comp>
    <comp ref="C22">
      <value>.1u</value>
      <footprint>Capacitors_SMD:C_0805_HandSoldering</footprint>
      <fields>
        <field name="PN">C</field>
      </fields>
      <libsource lib="device" part="C"/>
      <sheetpath names="/ATM90_Circuit/" tstamps="/5A1041CA/"/>
      <tstamp>5A2476CC</tstamp>
    </comp>
  </components>
  <libparts>
    <libpart lib="ATM90E26_Featherwing" part="ATM90E26_ATM90E26">
      <footprints>
        <fp>*ATM90E26_SSOP-28*</fp>
      </footprints>
      <fields>
        <field name="Reference">M</field>
        <field name="Value">ATM90E26_ATM90E26</field>
      </fields>
      <pins>
        <pin num="1" name="MMD1" type="input"/>
        <pin num="2" name="DGND" type="power_in"/>
        <pin num="3" name="DVDD" type="power_in"/>
        <pin num="4" name="~RESET" type="input"/>
        <pin num="5" name="AVDD" type="power_in"/>
        <pin num="6" name="AGND" type="power_in"/>
        <pin num="7" name="I2P" type="NotConnected"/>
        <pin num="8" name="I2N" type="NotConnected"/>
        <pin num="9" name="~RESV" type="input"/>
        <pin num="10" name="I1P" type="input"/>
        <pin num="11" name="I1N" type="input"/>
        <pin num="12" name="USEL" type="input"/>
        <pin num="13" name="VREF" type="power_out"/>
        <pin num="14" name="AGND" type="power_in"/>
        <pin num="15" name="VN" type="input"/>
        <pin num="16" name="VP" type="input"/>
        <pin num="17" name="WARNOUT" type="NotConnected"/>
        <pin num="18" name="CF1" type="NotConnected"/>
        <pin num="19" name="CF2" type="NotConnected"/>
        <pin num="20" name="IRQ" type="NotConnected"/>
        <pin num="21" name="ZX" type="NotConnected"/>
        <pin num="22" name="OSCI" type="input"/>
        <pin num="23" name="OSCO" type="output"/>
        <pin num="24" name="~CS" type="input"/>
        <pin num="25" name="SCLK" type="input"/>
        <pin num="26" name="SDO/UTX" type="output"/>
        <pin num="27" name="SDI/URX" type="input"/>
        <pin num="28" name="MMD0" type="input"/>
      </pins>
    </libpart>
    <libpart lib="device" part="C">
      <description>Unpolarized capacitor</description>
      <footprints>
        <fp>C_*</fp>
      </footprints>
      <fields>
        <field name="Reference">C</field>
        <field name="Value">C</field>
      </fields>
      <pins>
        <pin num="1" name="~" type="passive"/>
        <pin num="2" name="~" type="passive"/>
      </pins>
    </libpart>
    <libpart lib="device" part="CP1">
      <description>Polarised capacitor</description>
      <footprints>
        <fp>CP_*</fp>
      </footprints>
      <fields>
        <field name="Reference">C</field>
        <field name="Value">CP1</field>
      </fields>
      <pins>
        <pin num="1" name="~" type="passive"/>
        <pin num="2" name="~" type="passive"/>
      </pins>
    </libpart>
    <libpart lib="conn" part="Conn_01x03">
      <description>Generic connector, single row, 01x03</description>
      <docs>~</docs>
      <footprints>
        <fp>Connector*:*_??x*mm*</fp>
        <fp>Connector*:*1x??x*mm*</fp>
        <fp>Pin?Header?Straight?1X*</fp>
        <fp>Pin?Header?Angled?1X*</fp>
        <fp>Socket?Strip?Straight?1X*</fp>
        <fp>Socket?Strip?Angled?1X*</fp>
      </footprints>
      <fields>
        <field name="Reference">J</field>
        <field name="Value">Conn_01x03</field>
      </fields>
      <pins>
        <pin num="1" name="Pin_1" type="passive"/>
        <pin num="2" name="Pin_2" type="passive"/>
        <pin num="3" name="Pin_3" type="passive"/>
      </pins>
    </libpart>
    <libpart lib="device" part="Crystal_Small">
      <description>Two pin crystal, small symbol</description>
      <footprints>
        <fp>Crystal*</fp>
      </footprints>
      <fields>
        <field name="Reference">Y</field>
        <field name="Value">Crystal_Small</field>
      </fields>
      <pins>
        <pin num="1" name="1" type="passive"/>
        <pin num="2" name="2" type="passive"/>
      </pins>
    </libpart>
    <libpart lib="atm90e26" part="FeatherHuzzah">
      <fields>
        <field name="Reference">U</field>
        <field name="Value">FeatherHuzzah</field>
      </fields>
      <pins>
        <pin num="1" name="3" type="NotConnected"/>
        <pin num="2" name="TX" type="NotConnected"/>
        <pin num="3" name="RX" type="NotConnected"/>
        <pin num="4" name="MISO" type="input"/>
        <pin num="5" name="MOSI" type="output"/>
        <pin num="6" name="SCK" type="output"/>
        <pin num="7" name="NC" type="NotConnected"/>
        <pin num="8" name="NC" type="NotConnected"/>
        <pin num="9" name="NC" type="NotConnected"/>
        <pin num="10" name="NC" type="NotConnected"/>
        <pin num="11" name="NC" type="NotConnected"/>
        <pin num="12" name="ADC" type="NotConnected"/>
        <pin num="13" name="GND" type="input"/>
        <pin num="14" name="NC" type="NotConnected"/>
        <pin num="15" name="3V3" type="output"/>
        <pin num="16" name="RST" type="NotConnected"/>
        <pin num="17" name="BAT" type="input"/>
        <pin num="18" name="EN" type="BiDi"/>
        <pin num="19" name="USB" type="NotConnected"/>
        <pin num="20" name="5" type="NotConnected"/>
        <pin num="21" name="6" type="NotConnected"/>
        <pin num="22" name="7" type="NotConnected"/>
        <pin num="23" name="CS1" type="output"/>
        <pin num="24" name="CS0" type="output"/>
        <pin num="25" name="4" type="NotConnected"/>
        <pin num="26" name="11" type="NotConnected"/>
        <pin num="27" name="SCL" type="NotConnected"/>
        <pin num="28" name="SDA" type="NotConnected"/>
      </pins>
    </libpart>
    <libpart lib="device" part="Ferrite_Bead_Small">
      <description>Ferrite bead, small symbol</description>
      <footprints>
        <fp>Inductor_*</fp>
        <fp>L_*</fp>
        <fp>*Ferrite*</fp>
      </footprints>
      <fields>
        <field name="Reference">L</field>
        <field name="Value">Ferrite_Bead_Small</field>
      </fields>
      <pins>
        <pin num="1" name="~" type="passive"/>
        <pin num="2" name="~" type="passive"/>
      </pins>
    </libpart>
    <libpart lib="conn" part="GS3">
      <description>3-pin jumper/solder bridge</description>
      <footprints>
        <fp>GS*</fp>
      </footprints>
      <fields>
        <field name="Reference">J</field>
        <field name="Value">GS3</field>
        <field name="Footprint">Connectors:GS3</field>
      </fields>
      <pins>
        <pin num="1" name="G1" type="passive"/>
        <pin num="2" name="G2" type="passive"/>
        <pin num="3" name="G3" type="passive"/>
      </pins>
    </libpart>
    <libpart lib="device" part="LED">
      <description>LED generic</description>
      <footprints>
        <fp>LED*</fp>
      </footprints>
      <fields>
        <field name="Reference">D</field>
        <field name="Value">LED</field>
      </fields>
      <pins>
        <pin num="1" name="K" type="passive"/>
        <pin num="2" name="A" type="passive"/>
      </pins>
    </libpart>
    <libpart lib="device" part="L_Core_Ferrite_Small">
      <description>Inductor with ferrite core, small symbol</description>
      <footprints>
        <fp>Choke_*</fp>
        <fp>*Coil*</fp>
        <fp>Inductor_*</fp>
        <fp>L_*</fp>
      </footprints>
      <fields>
        <field name="Reference">L</field>
        <field name="Value">L_Core_Ferrite_Small</field>
      </fields>
      <pins>
        <pin num="1" name="~" type="passive"/>
        <pin num="2" name="~" type="passive"/>
      </pins>
    </libpart>
    <libpart lib="device" part="Polyfuse">
      <description>resettable fuse, polymeric positive temperature coefficient (PPTC)</description>
      <footprints>
        <fp>*polyfuse*</fp>
        <fp>*PTC*</fp>
      </footprints>
      <fields>
        <field name="Reference">F</field>
        <field name="Value">Polyfuse</field>
      </fields>
      <pins>
        <pin num="1" name="~" type="passive"/>
        <pin num="2" name="~" type="passive"/>
      </pins>
    </libpart>
    <libpart lib="device" part="R">
      <description>Resistor</description>
      <footprints>
        <fp>R_*</fp>
        <fp>R_*</fp>
      </footprints>
      <fields>
        <field name="Reference">R</field>
        <field name="Value">R</field>
      </fields>
      <pins>
        <pin num="1" name="~" type="passive"/>
        <pin num="2" name="~" type="passive"/>
      </pins>
    </libpart>
    <libpart lib="atm90e26" part="RAC03-3.3SGA">
      <fields>
        <field name="Reference">U</field>
        <field name="Value">RAC03-3.3SGA</field>
      </fields>
      <pins>
        <pin num="1" name="L" type="input"/>
        <pin num="3" name="N" type="input"/>
        <pin num="4" name="-VO" type="output"/>
        <pin num="5" name="+VO" type="output"/>
      </pins>
    </libpart>
    <libpart lib="si865" part="Si8655">
      <footprints>
        <fp>QSOP-16</fp>
      </footprints>
      <fields>
        <field name="Reference">U</field>
        <field name="Value">Si8655</field>
        <field name="Footprint">QSOP-16</field>
      </fields>
      <pins>
        <pin num="1" name="VDD1" type="BiDi"/>
        <pin num="2" name="A1" type="input"/>
        <pin num="3" name="A2" type="input"/>
        <pin num="4" name="A3" type="input"/>
        <pin num="5" name="A4" type="input"/>
        <pin num="6" name="A5" type="output"/>
        <pin num="7" name="NC" type="NotConnected"/>
        <pin num="8" name="GND1" type="BiDi"/>
        <pin num="9" name="GND2" type="BiDi"/>
        <pin num="10" name="EN2" type="BiDi"/>
        <pin num="11" name="B5" type="input"/>
        <pin num="12" name="B4" type="output"/>
        <pin num="13" name="B3" type="output"/>
        <pin num="14" name="B2" type="output"/>
        <pin num="15" name="B1" type="output"/>
        <pin num="16" name="VDD2" type="BiDi"/>
      </pins>
    </libpart>
    <libpart lib="device" part="TEST">
      <description>Testpoint, connection for test equipment</description>
      <fields>
        <field name="Reference">TP</field>
        <field name="Value">TEST</field>
      </fields>
      <pins>
        <pin num="1" name="~" type="passive"/>
      </pins>
    </libpart>
    <libpart lib="atm90e26" part="TRS3.5Female">
      <description>5-pin (audio) jack receptable (TRRRS connector)</description>
      <docs>~</docs>
      <fields>
        <field name="Reference">J</field>
        <field name="Value">TRS3.5Female</field>
      </fields>
      <pins>
        <pin num="1" name="sleeve" type="output"/>
        <pin num="2" name="tip" type="output"/>
        <pin num="3" name="ring" type="NotConnected"/>
      </pins>
    </libpart>
    <libpart lib="device" part="Varistor">
      <description>Voltage dependent resistor</description>
      <footprints>
        <fp>RV_*</fp>
        <fp>Varistor*</fp>
      </footprints>
      <fields>
        <field name="Reference">RV</field>
        <field name="Value">Varistor</field>
      </fields>
      <pins>
        <pin num="1" name="~" type="passive"/>
        <pin num="2" name="~" type="passive"/>
      </pins>
    </libpart>
    <libpart lib="dc-dc" part="dc-dc">
      <fields>
        <field name="Reference">U</field>
        <field name="Value">dc-dc</field>
      </fields>
      <pins>
        <pin num="1" name="IN-" type="power_in"/>
        <pin num="2" name="IN+" type="power_in"/>
        <pin num="3" name="OUT-" type="power_out"/>
        <pin num="4" name="OUT+" type="power_out"/>
      </pins>
    </libpart>
  </libparts>
  <libraries>
    <library logical="device">
      <uri>/Library/Application Support/kicad/library/device.lib</uri>
    </library>
    <library logical="conn">
      <uri>/Library/Application Support/kicad/library/conn.lib</uri>
    </library>
    <library logical="si865">
      <uri>/Users/margaret/Documents/EnergyMonitoring/HappyDayNeighbors/HappyDay_Energy_PCB/libs/si865.lib</uri>
    </library>
    <library logical="ATM90E26_Featherwing">
      <uri>/Users/margaret/Documents/EnergyMonitoring/HappyDayNeighbors/HappyDay_Energy_PCB/libs/ATM90E26_Featherwing.lib</uri>
    </library>
    <library logical="dc-dc">
      <uri>/Users/margaret/Documents/EnergyMonitoring/HappyDayNeighbors/HappyDay_Energy_PCB/libs/dc-dc.lib</uri>
    </library>
    <library logical="atm90e26">
      <uri>/Users/margaret/Documents/EnergyMonitoring/HappyDayNeighbors/HappyDay_Energy_PCB/libs/atm90e26.lib</uri>
    </library>
  </libraries>
  <nets>
    <net code="1" name="Net-(D2-Pad1)">
      <node ref="D2" pin="1"/>
      <node ref="R13" pin="1"/>
    </net>
    <net code="2" name="Net-(R5-Pad1)">
      <node ref="R5" pin="1"/>
      <node ref="R7" pin="2"/>
    </net>
    <net code="3" name="Net-(R7-Pad1)">
      <node ref="R7" pin="1"/>
      <node ref="R9" pin="2"/>
    </net>
    <net code="4" name="Net-(R4-Pad1)">
      <node ref="R4" pin="1"/>
      <node ref="R6" pin="2"/>
    </net>
    <net code="5" name="GND_MCU">
      <node ref="R13" pin="2"/>
      <node ref="TP11" pin="1"/>
      <node ref="U1" pin="4"/>
      <node ref="U3" pin="8"/>
      <node ref="C22" pin="2"/>
      <node ref="U4" pin="13"/>
      <node ref="C6" pin="2"/>
      <node ref="U2" pin="1"/>
    </net>
    <net code="6" name="GNDA">
      <node ref="U2" pin="3"/>
      <node ref="L1" pin="2"/>
      <node ref="C2" pin="2"/>
      <node ref="R12" pin="1"/>
      <node ref="C1" pin="2"/>
      <node ref="R11" pin="1"/>
      <node ref="L3" pin="1"/>
      <node ref="C5" pin="2"/>
      <node ref="C3" pin="2"/>
      <node ref="TP2" pin="1"/>
    </net>
    <net code="7" name="Net-(R3-Pad1)">
      <node ref="R5" pin="2"/>
      <node ref="R3" pin="1"/>
    </net>
    <net code="8" name="L0">
      <node ref="RV1" pin="2"/>
      <node ref="U1" pin="1"/>
      <node ref="R3" pin="2"/>
      <node ref="J1" pin="1"/>
      <node ref="C3" pin="1"/>
      <node ref="C4" pin="1"/>
    </net>
    <net code="10" name="Net-(C4-Pad2)">
      <node ref="C4" pin="2"/>
      <node ref="U1" pin="3"/>
      <node ref="C5" pin="1"/>
      <node ref="F1" pin="1"/>
    </net>
    <net code="11" name="I1P_0">
      <node ref="R1" pin="2"/>
      <node ref="TP6" pin="1"/>
      <node ref="M1" pin="10"/>
      <node ref="J2" pin="2"/>
    </net>
    <net code="12" name="I1N_0">
      <node ref="TP7" pin="1"/>
      <node ref="R1" pin="1"/>
      <node ref="M1" pin="11"/>
      <node ref="J2" pin="1"/>
    </net>
    <net code="13" name="N">
      <node ref="L1" pin="1"/>
      <node ref="RV2" pin="1"/>
      <node ref="F1" pin="2"/>
      <node ref="M2" pin="15"/>
      <node ref="J1" pin="3"/>
      <node ref="RV1" pin="1"/>
      <node ref="M1" pin="15"/>
    </net>
    <net code="14" name="Net-(R6-Pad1)">
      <node ref="R8" pin="2"/>
      <node ref="R6" pin="1"/>
    </net>
    <net code="15" name="Net-(R10-Pad2)">
      <node ref="R10" pin="2"/>
      <node ref="R8" pin="1"/>
    </net>
    <net code="16" name="Net-(J2-Pad3)">
      <node ref="J2" pin="3"/>
    </net>
    <net code="17" name="I1N_1">
      <node ref="R2" pin="1"/>
      <node ref="J3" pin="1"/>
      <node ref="TP9" pin="1"/>
      <node ref="M2" pin="11"/>
    </net>
    <net code="18" name="I1P_1">
      <node ref="R2" pin="2"/>
      <node ref="J3" pin="2"/>
      <node ref="TP8" pin="1"/>
      <node ref="M2" pin="10"/>
    </net>
    <net code="19" name="Net-(J3-Pad3)">
      <node ref="J3" pin="3"/>
    </net>
    <net code="20" name="3.3V_REG_A">
      <node ref="TP1" pin="1"/>
      <node ref="L2" pin="1"/>
      <node ref="U2" pin="4"/>
    </net>
    <net code="21" name="3.3V_MCU">
      <node ref="R24" pin="2"/>
      <node ref="C6" pin="1"/>
      <node ref="U1" pin="5"/>
      <node ref="U4" pin="15"/>
      <node ref="U4" pin="17"/>
      <node ref="C22" pin="1"/>
      <node ref="U3" pin="1"/>
      <node ref="U2" pin="2"/>
      <node ref="D2" pin="2"/>
      <node ref="TP10" pin="1"/>
    </net>
    <net code="22" name="L1">
      <node ref="RV2" pin="2"/>
      <node ref="J1" pin="2"/>
      <node ref="R4" pin="2"/>
    </net>
    <net code="23" name="L0_SAMP">
      <node ref="M1" pin="16"/>
      <node ref="TP3" pin="1"/>
      <node ref="R9" pin="1"/>
      <node ref="R11" pin="2"/>
      <node ref="C1" pin="1"/>
    </net>
    <net code="24" name="L1_SAMP">
      <node ref="R12" pin="2"/>
      <node ref="C2" pin="1"/>
      <node ref="TP4" pin="1"/>
      <node ref="R10" pin="1"/>
      <node ref="M2" pin="16"/>
    </net>
    <net code="25" name="CS0_MCU">
      <node ref="U4" pin="23"/>
      <node ref="R15" pin="2"/>
    </net>
    <net code="26" name="CS1_MCU">
      <node ref="U4" pin="24"/>
      <node ref="R14" pin="2"/>
    </net>
    <net code="27" name="SCLK_MCU">
      <node ref="U4" pin="6"/>
      <node ref="R17" pin="2"/>
    </net>
    <net code="28" name="MOSI_MCU">
      <node ref="U4" pin="5"/>
      <node ref="R16" pin="2"/>
    </net>
    <net code="29" name="MISO_MCU">
      <node ref="U4" pin="4"/>
      <node ref="R18" pin="2"/>
    </net>
    <net code="30" name="CLKIN_1">
      <node ref="Y2" pin="2"/>
      <node ref="M2" pin="22"/>
      <node ref="C16" pin="1"/>
    </net>
    <net code="31" name="CLKOUT_1">
      <node ref="C15" pin="1"/>
      <node ref="Y2" pin="1"/>
      <node ref="M2" pin="23"/>
    </net>
    <net code="32" name="CS0_ATM">
      <node ref="M1" pin="24"/>
      <node ref="R20" pin="1"/>
    </net>
    <net code="33" name="Net-(R23-Pad2)">
      <node ref="R23" pin="2"/>
      <node ref="U3" pin="11"/>
    </net>
    <net code="34" name="Net-(R22-Pad2)">
      <node ref="R22" pin="2"/>
      <node ref="U3" pin="12"/>
    </net>
    <net code="35" name="Net-(R21-Pad2)">
      <node ref="R21" pin="2"/>
      <node ref="U3" pin="13"/>
    </net>
    <net code="36" name="Net-(R20-Pad2)">
      <node ref="U3" pin="14"/>
      <node ref="R20" pin="2"/>
    </net>
    <net code="37" name="Net-(R19-Pad2)">
      <node ref="R19" pin="2"/>
      <node ref="U3" pin="15"/>
    </net>
    <net code="38" name="Net-(C19-Pad1)">
      <node ref="C21" pin="1"/>
      <node ref="C19" pin="1"/>
      <node ref="M2" pin="13"/>
    </net>
    <net code="39" name="MOSI_ATM">
      <node ref="M1" pin="27"/>
      <node ref="M2" pin="27"/>
      <node ref="R21" pin="1"/>
    </net>
    <net code="40" name="MISO_ATM">
      <node ref="R23" pin="1"/>
      <node ref="M1" pin="26"/>
      <node ref="M2" pin="26"/>
    </net>
    <net code="41" name="CS1_ATM">
      <node ref="R19" pin="1"/>
      <node ref="M2" pin="24"/>
    </net>
    <net code="42" name="SCLK_ATM">
      <node ref="M2" pin="25"/>
      <node ref="R22" pin="1"/>
      <node ref="M1" pin="25"/>
    </net>
    <net code="43" name="GNDD">
      <node ref="C16" pin="2"/>
      <node ref="M2" pin="12"/>
      <node ref="C15" pin="2"/>
      <node ref="M2" pin="9"/>
      <node ref="J17" pin="1"/>
      <node ref="J18" pin="3"/>
      <node ref="C8" pin="1"/>
      <node ref="C10" pin="2"/>
      <node ref="C12" pin="2"/>
      <node ref="C9" pin="2"/>
      <node ref="C11" pin="2"/>
      <node ref="J11" pin="3"/>
      <node ref="C20" pin="2"/>
      <node ref="C18" pin="2"/>
      <node ref="J10" pin="1"/>
      <node ref="C17" pin="1"/>
      <node ref="C14" pin="2"/>
      <node ref="L3" pin="2"/>
      <node ref="C13" pin="2"/>
      <node ref="U3" pin="9"/>
      <node ref="M1" pin="14"/>
      <node ref="M1" pin="12"/>
      <node ref="C7" pin="2"/>
      <node ref="M2" pin="2"/>
      <node ref="M1" pin="9"/>
      <node ref="M1" pin="6"/>
      <node ref="M1" pin="2"/>
      <node ref="M2" pin="6"/>
    </net>
    <net code="44" name="Net-(C19-Pad2)">
      <node ref="M2" pin="14"/>
      <node ref="C19" pin="2"/>
      <node ref="C21" pin="2"/>
    </net>
    <net code="45" name="Net-(U3-Pad7)">
      <node ref="U3" pin="7"/>
    </net>
    <net code="46" name="Net-(M1-Pad19)">
      <node ref="M1" pin="19"/>
    </net>
    <net code="47" name="Net-(M1-Pad18)">
      <node ref="M1" pin="18"/>
    </net>
    <net code="48" name="Net-(M1-Pad17)">
      <node ref="M1" pin="17"/>
    </net>
    <net code="49" name="Net-(M1-Pad21)">
      <node ref="M1" pin="21"/>
    </net>
    <net code="50" name="+3.3VA">
      <node ref="C20" pin="1"/>
      <node ref="C18" pin="1"/>
      <node ref="C7" pin="1"/>
      <node ref="J17" pin="3"/>
      <node ref="J18" pin="1"/>
      <node ref="C17" pin="2"/>
      <node ref="L2" pin="2"/>
      <node ref="U3" pin="10"/>
      <node ref="M1" pin="3"/>
      <node ref="M1" pin="4"/>
      <node ref="M1" pin="5"/>
      <node ref="U3" pin="16"/>
      <node ref="M2" pin="3"/>
      <node ref="M2" pin="4"/>
      <node ref="M2" pin="5"/>
      <node ref="J10" pin="3"/>
      <node ref="J11" pin="1"/>
      <node ref="C11" pin="1"/>
      <node ref="C9" pin="1"/>
      <node ref="C8" pin="2"/>
    </net>
    <net code="51" name="/ATM90_Circuit/MISO">
      <node ref="R18" pin="1"/>
      <node ref="U3" pin="6"/>
    </net>
    <net code="52" name="/ATM90_Circuit/CS1">
      <node ref="U3" pin="2"/>
      <node ref="R14" pin="1"/>
    </net>
    <net code="53" name="/ATM90_Circuit/CS0">
      <node ref="R15" pin="1"/>
      <node ref="U3" pin="3"/>
    </net>
    <net code="54" name="/ATM90_Circuit/MOSI">
      <node ref="U3" pin="4"/>
      <node ref="R16" pin="1"/>
    </net>
    <net code="55" name="/ATM90_Circuit/SCK">
      <node ref="R17" pin="1"/>
      <node ref="U3" pin="5"/>
    </net>
    <net code="56" name="Net-(U4-Pad19)">
      <node ref="U4" pin="19"/>
    </net>
    <net code="57" name="Net-(U4-Pad28)">
      <node ref="U4" pin="28"/>
    </net>
    <net code="58" name="Net-(R24-Pad1)">
      <node ref="U4" pin="18"/>
      <node ref="R24" pin="1"/>
    </net>
    <net code="59" name="Net-(U4-Pad27)">
      <node ref="U4" pin="27"/>
    </net>
    <net code="60" name="Net-(U4-Pad26)">
      <node ref="U4" pin="26"/>
    </net>
    <net code="61" name="Net-(U4-Pad25)">
      <node ref="U4" pin="25"/>
    </net>
    <net code="62" name="Net-(U4-Pad22)">
      <node ref="U4" pin="22"/>
    </net>
    <net code="63" name="Net-(U4-Pad21)">
      <node ref="U4" pin="21"/>
    </net>
    <net code="64" name="Net-(U4-Pad20)">
      <node ref="U4" pin="20"/>
    </net>
    <net code="65" name="Net-(M2-Pad7)">
      <node ref="M2" pin="7"/>
    </net>
    <net code="66" name="Net-(U4-Pad16)">
      <node ref="U4" pin="16"/>
    </net>
    <net code="67" name="Net-(U4-Pad14)">
      <node ref="U4" pin="14"/>
    </net>
    <net code="68" name="Net-(U4-Pad12)">
      <node ref="U4" pin="12"/>
    </net>
    <net code="69" name="Net-(U4-Pad11)">
      <node ref="U4" pin="11"/>
    </net>
    <net code="70" name="Net-(U4-Pad10)">
      <node ref="U4" pin="10"/>
    </net>
    <net code="71" name="Net-(U4-Pad9)">
      <node ref="U4" pin="9"/>
    </net>
    <net code="72" name="Net-(U4-Pad8)">
      <node ref="U4" pin="8"/>
    </net>
    <net code="73" name="Net-(U4-Pad7)">
      <node ref="U4" pin="7"/>
    </net>
    <net code="74" name="Net-(U4-Pad3)">
      <node ref="U4" pin="3"/>
    </net>
    <net code="75" name="Net-(U4-Pad2)">
      <node ref="U4" pin="2"/>
    </net>
    <net code="76" name="Net-(U4-Pad1)">
      <node ref="U4" pin="1"/>
    </net>
    <net code="77" name="Net-(M1-Pad20)">
      <node ref="M1" pin="20"/>
    </net>
    <net code="78" name="Net-(M1-Pad8)">
      <node ref="M1" pin="8"/>
    </net>
    <net code="79" name="Net-(M1-Pad7)">
      <node ref="M1" pin="7"/>
    </net>
    <net code="80" name="Net-(M2-Pad19)">
      <node ref="M2" pin="19"/>
    </net>
    <net code="81" name="Net-(M2-Pad18)">
      <node ref="M2" pin="18"/>
    </net>
    <net code="82" name="Net-(M2-Pad17)">
      <node ref="M2" pin="17"/>
    </net>
    <net code="83" name="Net-(M2-Pad21)">
      <node ref="M2" pin="21"/>
    </net>
    <net code="84" name="Net-(M2-Pad20)">
      <node ref="M2" pin="20"/>
    </net>
    <net code="85" name="Net-(M2-Pad8)">
      <node ref="M2" pin="8"/>
    </net>
    <net code="86" name="CLKIN_0">
      <node ref="M1" pin="22"/>
      <node ref="Y1" pin="2"/>
      <node ref="C14" pin="1"/>
    </net>
    <net code="87" name="CLKOUT_0">
      <node ref="C13" pin="1"/>
      <node ref="M1" pin="23"/>
      <node ref="Y1" pin="1"/>
    </net>
    <net code="88" name="Net-(C10-Pad1)">
      <node ref="M1" pin="13"/>
      <node ref="C12" pin="1"/>
      <node ref="C10" pin="1"/>
    </net>
    <net code="89" name="Net-(J11-Pad2)">
      <node ref="M1" pin="28"/>
      <node ref="J11" pin="2"/>
    </net>
    <net code="90" name="Net-(J10-Pad2)">
      <node ref="J10" pin="2"/>
      <node ref="M1" pin="1"/>
    </net>
    <net code="91" name="Net-(J18-Pad2)">
      <node ref="M2" pin="28"/>
      <node ref="J18" pin="2"/>
    </net>
    <net code="92" name="Net-(J17-Pad2)">
      <node ref="J17" pin="2"/>
      <node ref="M2" pin="1"/>
    </net>
  </nets>
</export>
